chatbot_fifa_extension/__init__.py
chatbot_fifa_extension/euro2024.py
chatbot_fifa_extension/exceptions.py
chatbot_fifa_extension/fifa.py
chatbot_fifa_extension/memories.py
chatbot_fifa_extension-0.0.14.dist-info/LICENSE
chatbot_fifa_extension-0.0.14.dist-info/METADATA
chatbot_fifa_extension-0.0.14.dist-info/WHEEL
chatbot_fifa_extension-0.0.14.dist-info/top_level.txt
chatbot_fifa_extension-0.0.14.dist-info/RECORD
