Metadata-Version: 2.1
Name: chatbot_fifa_extension
Version: 0.0.14
Summary: FIFA World Cup chatbot extension
Home-page: https://github.com/Kolumbs/chatbot-fifa-extension
Author: Juris Kaminskis
Author-email: juris@zoozl.net
Requires-Python: >=3.10
License-File: LICENSE
Requires-Dist: zoozl>=0.1.4
Requires-Dist: membank>=0.4.1
